LICENSE
README.md
__init__.py
pyproject.toml
setup.cfg
setup.py
.idea/libs.iml
.idea/modules.xml
src/__init__.py
src/dslibs/__init__.py
src/dslibs/cross_validation_score.py
src/dslibs/mglearn.py
src/dslibs/simple_analyzer.py
src/dslibs/simple_hyper_tuner.py
src/dslibs/simple_processing.py
src/dslibs/simple_reducer.py
src/dslibs/simple_yahoo.py
src/dslibs/simpleplotter.py
src/dslibs/single_scoring.py
src/dslibs.egg-info/PKG-INFO
src/dslibs.egg-info/SOURCES.txt
src/dslibs.egg-info/dependency_links.txt
src/dslibs.egg-info/not-zip-safe
src/dslibs.egg-info/requires.txt
src/dslibs.egg-info/top_level.txt
src/dslibs/dl/simple_hypertuner.py
src/dslibs/dl/simple_regressor.py