Metadata-Version: 2.1
Name: dslibs
Version: 0.0.7
Summary: data science related tools & helpers
Home-page: https://github.com/cjkepinsky/libs
Author: Chris J. Kepinsky
Author-email: chris.kepinski@gmail.com
License: MIT
Project-URL: Bug Tracker, https://github.com/cjkepinsky/libs/issues
Platform: UNKNOWN
Classifier: Programming Language :: Python :: 3
Classifier: License :: OSI Approved :: MIT License
Classifier: Operating System :: OS Independent
Requires-Python: >=3.9
License-File: LICENSE
